comparisons/telemetrix_aio.py
examples/analog_input.py
examples/blink.py
examples/dht.py
examples/digital_input.py
examples/digital_input_pullup.py
examples/fade.py
examples/hc-sr04_distance_sensor.py
examples/i2c_adxl345_accelerometer.py
examples/i2c_adxl345_accelerometer2.py
examples/loop_back.py
examples/onewire_ds18x20.py
examples/servo.py
examples/sonar_disable.py
examples/spi_adxl345_accelerometer.py
examples/stepper_absolute.py
examples/stepper_continuous.py
examples/stepper_relative.py
examples/wifi/analog_input_wifi.py
examples/wifi/blink_wifi.py
examples/wifi/dht_wifi.py
examples/wifi/digital_input_wifi.py
examples/wifi/fade_wifi.py
examples/wifi/hc-sr04_distance_sensor_wifi.py
examples/wifi/i2c_adxl345_accelerometer_wifi.py
examples/wifi/loop_back_wifi.py
examples/wifi/onewire_ds18x20.py
examples/wifi/servo_wifi.py
examples/wifi/sonar_disable.py
examples/wifi/spi_mpu9250.py
examples/wifi/stepper_absolute_wifi.py
examples/wifi/stepper_continuous_wifi.py
examples/wifi/stepper_relative_wifi.py
telemetrix_aio/__init__.py
telemetrix_aio/private_constants.py
telemetrix_aio/telemetrix_aio.py
telemetrix_aio/telemetrix_aio_socket.py
telemetrix_aio/telemtrix_aio_serial.py
venv/bin/activate_this.py
venv2/bin/activate_this.py
telemetrix_aio-1.25.dist-info/METADATA
telemetrix_aio-1.25.dist-info/WHEEL
telemetrix_aio-1.25.dist-info/top_level.txt
telemetrix_aio-1.25.dist-info/RECORD
