Metadata-Version: 2.1
Name: telemetrix-aio
Version: 1.25
Summary: Telemetrix Client
Author-email: Alan Yorinks <MisterYsLab@gmail.com>
License: AGPL-3.0-or-later
Keywords: telemetrix,Arduino,UNO,ESP8266,Python
Classifier: Development Status :: 5 - Production/Stable
Classifier: Environment :: Other Environment
Classifier: Intended Audience :: Developers
Classifier: Intended Audience :: Education
Classifier: Operating System :: OS Independent
Classifier: Topic :: Software Development :: Libraries :: Python Modules
Requires-Python: >=3.8
Requires-Dist: pyserial
Requires-Dist: bleak
